elasticsearch_ir_evaluator/__init__.py
elasticsearch_ir_evaluator/evaluator.py
elasticsearch_ir_evaluator/types.py
tests/__init__.py
tests/test_evaluator.py
elasticsearch_ir_evaluator-0.4.4.dist-info/LICENSE
elasticsearch_ir_evaluator-0.4.4.dist-info/METADATA
elasticsearch_ir_evaluator-0.4.4.dist-info/WHEEL
elasticsearch_ir_evaluator-0.4.4.dist-info/top_level.txt
elasticsearch_ir_evaluator-0.4.4.dist-info/RECORD
