Metadata-Version: 2.1
Name: elasticsearch-ir-evaluator
Version: 0.4.4
Summary: A Python package for easily calculating information retrieval (IR) accuracy metrics using Elasticsearch and datasets.
Home-page: https://github.com/hinatades/elasticsearch-ir-evaluator
Author: Taisuke Hinata
Author-email: hnttisk@gmail.com
License: MIT
Requires-Python: >=3.8
License-File: LICENSE
Requires-Dist: elasticsearch >=8.11
Requires-Dist: numpy
Requires-Dist: pydantic
Requires-Dist: tqdm
